{
  "updates": {
    "items": [
      {
        "Title": "Creator Contest",
        "Banner": "https://dl-tata.freefireind.in/common/Local/IND/config/1400x700_CreatorContestSplash0105IND_en.jpg",
        "Start": "1767587400",
        "End": "1769884199",
        "LinkAlt": "https://www.instagram.com/p/DTHfd5siMUO/?img_index=1"
      },
      {
        "Title": "The Latest Updates",
        "Banner": "https://dl-tata.freefireind.in/common/Local/IND/config/1400x700_TheLatestUpdatesINDanno_en.jpg",
        "Start": "1742769000",
        "End": "4108904999",
        "LinkAlt": "https://www.instagram.com/freefireindiaofficial/"
      },
      {
        "Title": "Battle Card Mission",
        "Banner": "https://dl-tata.freefireind.in/common/Local/IND/config/336x580_Notice2_en.jpg",
        "Details": "Hi Survivors!\n\nWe’ve heard your feedback about the Jujutsu Battle Card mission. To make it more enjoyable and accessible for everyone, we've reduced the mission requirement for Itadori's Challenge to \"Deal 200 damage with Divergent Fist\".\n\nThanks for sharing your thoughts with us - your feedback helps us keep improving the game for all players. See you on the battlefield!",
        "Start": "1769140800",
        "End": "1772044199"
      },
      {
        "Title": "Watch the Battle Unfold",
        "Banner": "https://dl-tata.freefireind.in/common/Local/IND/config/1400x700_WatchTheBattleUnfoldINDAnno_en.jpg",
        "Start": "1742769000",
        "End": "4108904999",
        "LinkAlt": "https://www.youtube.com/@FreeFireIndiaOfficial"
      },
      {
        "Title": "Stay in the Loop",
        "Banner": "https://dl-tata.freefireind.in/common/Local/IND/config/1400x700_StayInLoopAnnIND_en.jpg",
        "Start": "1742769000",
        "End": "4108904999",
        "LinkAlt": "https://www.facebook.com/freefireIND"
      },
      {
        "Title": "Changes to JJK Weapons",
        "Banner": "https://dl-tata.freefireind.in/common/Local/IND/config/NoticeBanner_en.jpg",
        "Details": "Dear Survivors,\n\nWe’ve received feedback that the Desert Eagle - Recharge starts with only 7 rounds and pistol ammo is difficult to find in BR. We've made the following adjustments: you can now get 30 free pistol ammo in the Vending Machine for your Desert Eagle - Recharge.\n\nAdditionally, we’re still seeing feedback that the Kugisaki Hammer remains too strong and too easy to obtain. To address this, we’re increasing the price of the Hammer:\n\nHammer I: 50 (no change)\nHammer II: 50 → 100\nHammer III: 100 → 200\n\nThis change is live now.\n\nThank you for your continued feedback and support, and we wish you Happy Booyah!",
        "Start": "1769140800",
        "End": "1771007399"
      },
      {
        "Title": "Star Showcase",
        "Banner": "https://dl-tata.freefireind.in/common/Local/IND/config/1400x700_StarShowcaseAnnoIND_en.jpg",
        "Start": "1769574600",
        "End": "1769970599",
        "LinkAlt": "https://kolcricketleague.web.freefireindiamobile.com/?region=<FF_REGION>&lang=<FF_LANGUAGE>&access_token=<GARENA_TOKEN>"
      },
      {
        "Title": "Changes to JJK Hammer",
        "Banner": "https://dl-tata.freefireind.in/common/Local/IND/config/NoticeBanner_en.jpg",
        "Details": "Dear Survivors,\n\nWe've received feedbacks regarding the Jujutsu Hammer. Therefore, the stats of the Hammer will be adjusted to:\nKugisaki Hammer (Lv1/Lv2/Lv3):\nDamage: -15%\nLimb Damage: -25%\nMagazine Size: 12 → 5\n\nThe adjustments have been made. Thank you for your feedback and support!",
        "Start": "1768415400",
        "End": "1771007399"
      },
      {
        "Title": "How to participate",
        "Banner": "https://dl-tata.freefireind.in/common/Local/IND/config/1400x700_BPLHowToParticipateAnnoIND_en.jpg",
        "Start": "1769574600",
        "End": "1769970599",
        "LinkAlt": "https://kolcricketleague.web.freefireindiamobile.com/?region=<FF_REGION>&lang=<FF_LANGUAGE>&access_token=<GARENA_TOKEN>"
      },
      {
        "Title": "BPL Mastermind",
        "Banner": "https://dl-tata.freefireind.in/common/Local/IND/config/1400x700_BPLMastermindAnnoIND_en.jpg",
        "Start": "1769574600",
        "End": "1770402599",
        "LinkAlt": "https://kolcricketleague.web.freefireindiamobile.com/?region=<FF_REGION>&lang=<FF_LANGUAGE>&access_token=<GARENA_TOKEN>"
      }
    ]
  },
  "events": {
    "items": [
      {
        "Title": "JJK The Honored One",
        "Start": "1769639400",
        "End": "1769725799",
        "Link": "V2_category_5_groupID_95362",
        "Banner": "https://dl-tata.freefireind.in/common/Local/IND/config/1750x1070_TheHoneredOneNewSplashIND_en.jpg"
      },
      {
        "Title": "BPL Stream Full Day",
        "Start": "1769828400",
        "End": "1769877000"
      },
      {
        "Title": "Sukuna Ring: RYOMEN SUKUNA BUNDLE**",
        "Start": "1769639400",
        "End": "1769725799",
        "Link": "V2_chestId_89",
        "Banner": "https://dl-tata.freefireind.in/common/Local/IND/config/1750x1070_SukunaRingSplashIND_en.jpg"
      },
      {
        "Title": "BPL Mastermind",
        "Start": "1769725800",
        "End": "1769812199",
        "Link": "https://kolcricketleague.web.freefireindiamobile.com/?region=<FF_REGION>&lang=<FF_LANGUAGE>&access_token=<GARENA_TOKEN>",
        "Banner": "https://dl-tata.freefireind.in/common/Local/IND/config/1750x1070_BPLMastermindSplashIND_en.jpg"
      },
      {
        "Title": "JJK Special Grade Truck",
        "Start": "1769812200",
        "End": "1769898599",
        "Link": "V2_category_5_groupID_95361",
        "Banner": "https://dl-tata.freefireind.in/common/Local/IND/config/1750x1070_JJKSpecialGradeTruckIND_en.jpg"
      }
    ]
  }
}